synapse_to_ipynb.py
synapse_to_ipynb-1.2.1.dist-info/LICENSE
synapse_to_ipynb-1.2.1.dist-info/METADATA
synapse_to_ipynb-1.2.1.dist-info/WHEEL
synapse_to_ipynb-1.2.1.dist-info/entry_points.txt
synapse_to_ipynb-1.2.1.dist-info/top_level.txt
synapse_to_ipynb-1.2.1.dist-info/RECORD
