Metadata-Version: 2.1
Name: synapse-to-ipynb
Version: 1.2.1
Summary: Tool for managing and converting Synapse notebooks to Jupyter notebooks
Home-page: https://github.com/jordanamos/synapse-to-ipynb
Author: Jordan Amos
Author-email: jordan.amos@gmail.com
License: MIT
Keywords: synapse,jupyter,convert,ipynb,synch,notebook,notebooks
Classifier: License :: OSI Approved :: MIT License
Classifier: Natural Language :: English
Classifier: Programming Language :: Python
Classifier: Programming Language :: Python :: 3
Classifier: Programming Language :: Python :: 3 :: Only
Requires-Python: >=3.10
License-File: LICENSE
